p2r/__init__.py
p2r/p2r.py
p2r-0.2.2.dist-info/LICENSE
p2r-0.2.2.dist-info/METADATA
p2r-0.2.2.dist-info/WHEEL
p2r-0.2.2.dist-info/entry_points.txt
p2r-0.2.2.dist-info/top_level.txt
p2r-0.2.2.dist-info/RECORD
