Metadata-Version: 2.1
Name: p2r
Version: 0.2.2
Summary: PostmanScript to RequestsScript
Home-page: https://github.com/tser/p2r
Author: Tser
Author-email: 807447312@qq.com
License: UNKNOWN
Keywords: xiaobai p2r postman requests
Platform: UNKNOWN
Classifier: Programming Language :: Python :: 3
Classifier: License :: OSI Approved :: Apache Software License
Classifier: Operating System :: OS Independent
Requires-Python: >=3.4
Requires-Dist: requests
